LICENSE
README.md
setup.py
testpackage/__init__.py
testpackage/check_version.py
testpackage/document_extractor.py
testpackage/evaluation_question_generator.py
testpackage/hub.py
testpackage/library_exceptions.py
testpackage/text_chunker.py
testpackage/text_cleaner.py
testpackage/text_utils.py
testpackage/tru_lens_evaluator.py
testpackage123321.egg-info/PKG-INFO
testpackage123321.egg-info/SOURCES.txt
testpackage123321.egg-info/dependency_links.txt
testpackage123321.egg-info/entry_points.txt
testpackage123321.egg-info/requires.txt
testpackage123321.egg-info/top_level.txt